{
  "rooms": [
    {
      "code": "VV48X2",
      "hostUserId": "bac2c09d-4312-425b-89e1-871f07bf036e",
      "maxParticipants": 4,
      "questionCount": 3,
      "timeLimitMinutes": 45,
      "topics": [
        "Array",
        "Binary Search",
        "Dynamic Programming"
      ],
      "problemIds": [
        "c760e775-0e1e-45bd-9a44-a4e98cecf375",
        "02862102-e87c-418d-b396-f22ea083f911",
        "dddedc02-7c3c-4e0f-b3fe-3fbe9ec9ab18"
      ],
      "problemPoints": {
        "c760e775-0e1e-45bd-9a44-a4e98cecf375": 200,
        "02862102-e87c-418d-b396-f22ea083f911": 100,
        "dddedc02-7c3c-4e0f-b3fe-3fbe9ec9ab18": 200
      },
      "participants": [
        {
          "userId": "bac2c09d-4312-425b-89e1-871f07bf036e",
          "joinedAt": "2026-04-20T15:03:43.116Z"
        }
      ],
      "standings": {
        "bac2c09d-4312-425b-89e1-871f07bf036e": {
          "score": 0,
          "solvedProblemIds": [],
          "lastAcceptedAt": null
        }
      },
      "createdAt": "2026-04-20T15:03:43.116Z",
      "startsAt": "2026-04-20T15:03:43.116Z",
      "endsAt": "2026-04-20T15:48:43.116Z"
    },
    {
      "code": "KT2H8Z",
      "hostUserId": "bac2c09d-4312-425b-89e1-871f07bf036e",
      "maxParticipants": 4,
      "questionCount": 2,
      "timeLimitMinutes": 15,
      "topics": [
        "Array"
      ],
      "problemIds": [
        "c760e775-0e1e-45bd-9a44-a4e98cecf375",
        "dddedc02-7c3c-4e0f-b3fe-3fbe9ec9ab18"
      ],
      "problemPoints": {
        "c760e775-0e1e-45bd-9a44-a4e98cecf375": 200,
        "dddedc02-7c3c-4e0f-b3fe-3fbe9ec9ab18": 200
      },
      "participants": [
        {
          "userId": "bac2c09d-4312-425b-89e1-871f07bf036e",
          "joinedAt": "2026-04-20T15:06:31.873Z"
        }
      ],
      "standings": {
        "bac2c09d-4312-425b-89e1-871f07bf036e": {
          "score": 0,
          "solvedProblemIds": [],
          "lastAcceptedAt": null
        }
      },
      "createdAt": "2026-04-20T15:06:31.873Z",
      "startsAt": "2026-04-20T15:06:31.873Z",
      "endsAt": "2026-04-20T15:21:31.873Z"
    },
    {
      "code": "A7JE7B",
      "hostUserId": "bac2c09d-4312-425b-89e1-871f07bf036e",
      "maxParticipants": 4,
      "questionCount": 2,
      "timeLimitMinutes": 15,
      "topics": [
        "Array",
        "Binary Search"
      ],
      "problemIds": [
        "02862102-e87c-418d-b396-f22ea083f911",
        "dddedc02-7c3c-4e0f-b3fe-3fbe9ec9ab18"
      ],
      "problemPoints": {
        "02862102-e87c-418d-b396-f22ea083f911": 100,
        "dddedc02-7c3c-4e0f-b3fe-3fbe9ec9ab18": 200
      },
      "participants": [
        {
          "userId": "bac2c09d-4312-425b-89e1-871f07bf036e",
          "joinedAt": "2026-05-09T07:27:55.097Z"
        }
      ],
      "standings": {
        "bac2c09d-4312-425b-89e1-871f07bf036e": {
          "score": 0,
          "solvedProblemIds": [],
          "lastAcceptedAt": null
        }
      },
      "createdAt": "2026-05-09T07:27:55.097Z",
      "startsAt": "2026-05-09T07:27:55.097Z",
      "endsAt": "2026-05-09T07:42:55.097Z"
    },
    {
      "code": "7LK9EL",
      "hostUserId": "bac2c09d-4312-425b-89e1-871f07bf036e",
      "maxParticipants": 4,
      "questionCount": 1,
      "timeLimitMinutes": 30,
      "topics": [
        "Array",
        "Binary Search",
        "Dynamic Programming"
      ],
      "problemIds": [
        "c760e775-0e1e-45bd-9a44-a4e98cecf375"
      ],
      "problemPoints": {
        "c760e775-0e1e-45bd-9a44-a4e98cecf375": 200
      },
      "participants": [
        {
          "userId": "bac2c09d-4312-425b-89e1-871f07bf036e",
          "joinedAt": "2026-05-09T07:28:20.561Z"
        }
      ],
      "standings": {
        "bac2c09d-4312-425b-89e1-871f07bf036e": {
          "score": 0,
          "solvedProblemIds": [],
          "lastAcceptedAt": null
        }
      },
      "createdAt": "2026-05-09T07:28:20.561Z",
      "startsAt": "2026-05-09T07:28:20.561Z",
      "endsAt": "2026-05-09T07:58:20.561Z"
    },
    {
      "code": "DGJAXJ",
      "hostUserId": "bac2c09d-4312-425b-89e1-871f07bf036e",
      "maxParticipants": 4,
      "questionCount": 2,
      "timeLimitMinutes": 15,
      "topics": [
        "Array",
        "Binary Search"
      ],
      "problemIds": [
        "c760e775-0e1e-45bd-9a44-a4e98cecf375",
        "dddedc02-7c3c-4e0f-b3fe-3fbe9ec9ab18"
      ],
      "problemPoints": {
        "c760e775-0e1e-45bd-9a44-a4e98cecf375": 200,
        "dddedc02-7c3c-4e0f-b3fe-3fbe9ec9ab18": 200
      },
      "participants": [
        {
          "userId": "bac2c09d-4312-425b-89e1-871f07bf036e",
          "joinedAt": "2026-05-09T09:08:29.662Z"
        }
      ],
      "standings": {
        "bac2c09d-4312-425b-89e1-871f07bf036e": {
          "score": 0,
          "solvedProblemIds": [],
          "lastAcceptedAt": null
        }
      },
      "createdAt": "2026-05-09T09:08:29.662Z",
      "startsAt": "2026-05-09T09:08:29.662Z",
      "endsAt": "2026-05-09T09:23:29.662Z"
    },
    {
      "code": "52KKH2",
      "hostUserId": "bac2c09d-4312-425b-89e1-871f07bf036e",
      "maxParticipants": 4,
      "questionCount": 1,
      "timeLimitMinutes": 15,
      "topics": [
        "Array",
        "Binary Search"
      ],
      "problemIds": [
        "c760e775-0e1e-45bd-9a44-a4e98cecf375"
      ],
      "problemPoints": {
        "c760e775-0e1e-45bd-9a44-a4e98cecf375": 200
      },
      "participants": [
        {
          "userId": "bac2c09d-4312-425b-89e1-871f07bf036e",
          "joinedAt": "2026-05-09T09:30:55.311Z"
        }
      ],
      "standings": {
        "bac2c09d-4312-425b-89e1-871f07bf036e": {
          "score": 0,
          "solvedProblemIds": [],
          "lastAcceptedAt": null
        }
      },
      "createdAt": "2026-05-09T09:30:55.311Z",
      "startsAt": "2026-05-09T09:30:55.311Z",
      "endsAt": "2026-05-09T09:45:55.311Z"
    },
    {
      "code": "8T74AV",
      "hostUserId": "bac2c09d-4312-425b-89e1-871f07bf036e",
      "maxParticipants": 2,
      "questionCount": 2,
      "timeLimitMinutes": 30,
      "topics": [
        "Array",
        "Binary Search",
        "Dynamic Programming"
      ],
      "problemIds": [
        "c760e775-0e1e-45bd-9a44-a4e98cecf375",
        "dddedc02-7c3c-4e0f-b3fe-3fbe9ec9ab18"
      ],
      "problemPoints": {
        "c760e775-0e1e-45bd-9a44-a4e98cecf375": 200,
        "dddedc02-7c3c-4e0f-b3fe-3fbe9ec9ab18": 200
      },
      "participants": [
        {
          "userId": "bac2c09d-4312-425b-89e1-871f07bf036e",
          "joinedAt": "2026-05-09T10:05:26.917Z"
        }
      ],
      "standings": {
        "bac2c09d-4312-425b-89e1-871f07bf036e": {
          "score": 0,
          "solvedProblemIds": [],
          "lastAcceptedAt": null
        }
      },
      "createdAt": "2026-05-09T10:05:26.917Z",
      "startsAt": "2026-05-09T10:05:26.917Z",
      "endsAt": "2026-05-09T10:35:26.917Z"
    },
    {
      "code": "Z4TAW2",
      "hostUserId": "bac2c09d-4312-425b-89e1-871f07bf036e",
      "maxParticipants": 4,
      "questionCount": 3,
      "timeLimitMinutes": 45,
      "topics": [
        "Array",
        "Binary Search"
      ],
      "problemIds": [
        "dddedc02-7c3c-4e0f-b3fe-3fbe9ec9ab18",
        "02862102-e87c-418d-b396-f22ea083f911",
        "c760e775-0e1e-45bd-9a44-a4e98cecf375"
      ],
      "problemPoints": {
        "dddedc02-7c3c-4e0f-b3fe-3fbe9ec9ab18": 200,
        "02862102-e87c-418d-b396-f22ea083f911": 100,
        "c760e775-0e1e-45bd-9a44-a4e98cecf375": 200
      },
      "participants": [
        {
          "userId": "bac2c09d-4312-425b-89e1-871f07bf036e",
          "joinedAt": "2026-05-16T04:12:05.144Z"
        },
        {
          "userId": "4c333018-8317-4aa3-ae91-fe68242bd400",
          "joinedAt": "2026-05-16T04:13:02.322Z"
        },
        {
          "userId": "af3f2648-2f35-448d-b7d6-a6071df4369b",
          "joinedAt": "2026-05-16T04:14:36.679Z"
        }
      ],
      "standings": {
        "bac2c09d-4312-425b-89e1-871f07bf036e": {
          "score": 200,
          "solvedProblemIds": [
            "dddedc02-7c3c-4e0f-b3fe-3fbe9ec9ab18"
          ],
          "lastAcceptedAt": "2026-05-16T04:15:15.592Z"
        },
        "4c333018-8317-4aa3-ae91-fe68242bd400": {
          "score": 100,
          "solvedProblemIds": [
            "02862102-e87c-418d-b396-f22ea083f911"
          ],
          "lastAcceptedAt": "2026-05-16T04:16:17.762Z"
        },
        "af3f2648-2f35-448d-b7d6-a6071df4369b": {
          "score": 0,
          "solvedProblemIds": [],
          "lastAcceptedAt": null
        }
      },
      "createdAt": "2026-05-16T04:12:05.144Z",
      "startsAt": "2026-05-16T04:12:05.144Z",
      "endsAt": "2026-05-16T04:57:05.144Z"
    },
    {
      "code": "BLGZPE",
      "hostUserId": "bac2c09d-4312-425b-89e1-871f07bf036e",
      "maxParticipants": 4,
      "questionCount": 3,
      "timeLimitMinutes": 45,
      "topics": [
        "Array",
        "Binary Search"
      ],
      "problemIds": [
        "dddedc02-7c3c-4e0f-b3fe-3fbe9ec9ab18",
        "02862102-e87c-418d-b396-f22ea083f911",
        "c760e775-0e1e-45bd-9a44-a4e98cecf375"
      ],
      "problemPoints": {
        "dddedc02-7c3c-4e0f-b3fe-3fbe9ec9ab18": 200,
        "02862102-e87c-418d-b396-f22ea083f911": 100,
        "c760e775-0e1e-45bd-9a44-a4e98cecf375": 200
      },
      "participants": [
        {
          "userId": "bac2c09d-4312-425b-89e1-871f07bf036e",
          "joinedAt": "2026-05-22T08:35:24.154Z"
        }
      ],
      "standings": {
        "bac2c09d-4312-425b-89e1-871f07bf036e": {
          "score": 300,
          "solvedProblemIds": [
            "02862102-e87c-418d-b396-f22ea083f911",
            "dddedc02-7c3c-4e0f-b3fe-3fbe9ec9ab18"
          ],
          "lastAcceptedAt": "2026-05-22T08:36:26.469Z"
        }
      },
      "createdAt": "2026-05-22T08:35:24.154Z",
      "startsAt": "2026-05-22T08:35:24.154Z",
      "endsAt": "2026-05-22T09:20:24.154Z"
    },
    {
      "code": "R26RGR",
      "hostUserId": "bac2c09d-4312-425b-89e1-871f07bf036e",
      "maxParticipants": 4,
      "questionCount": 2,
      "timeLimitMinutes": 30,
      "topics": [
        "Array",
        "Binary Search",
        "String"
      ],
      "problemIds": [
        "c48c77b4-983a-4bf1-b145-6d11ee617130",
        "ec1569da-9fd8-4902-bf94-bd820962ddb1"
      ],
      "problemPoints": {
        "c48c77b4-983a-4bf1-b145-6d11ee617130": 100,
        "ec1569da-9fd8-4902-bf94-bd820962ddb1": 100
      },
      "participants": [
        {
          "userId": "bac2c09d-4312-425b-89e1-871f07bf036e",
          "joinedAt": "2026-06-04T21:43:29.830Z"
        },
        {
          "userId": "4c333018-8317-4aa3-ae91-fe68242bd400",
          "joinedAt": "2026-06-04T21:44:35.749Z"
        }
      ],
      "standings": {
        "bac2c09d-4312-425b-89e1-871f07bf036e": {
          "score": 0,
          "solvedProblemIds": [],
          "lastAcceptedAt": null
        },
        "4c333018-8317-4aa3-ae91-fe68242bd400": {
          "score": 0,
          "solvedProblemIds": [],
          "lastAcceptedAt": null
        }
      },
      "createdAt": "2026-06-04T21:43:29.830Z",
      "startsAt": "2026-06-04T21:43:29.830Z",
      "endsAt": "2026-06-04T22:13:29.830Z"
    },
    {
      "code": "K99QD4",
      "hostUserId": "0536f06a-b2cd-4510-8df6-49bec2bc3531",
      "maxParticipants": 8,
      "questionCount": 2,
      "timeLimitMinutes": 30,
      "topics": [
        "Array",
        "Binary Search"
      ],
      "problemIds": [
        "19635183-7f00-44d4-a48c-67e56322a9bc",
        "c63b68d6-6cb0-4636-8f08-673610064866"
      ],
      "problemPoints": {
        "19635183-7f00-44d4-a48c-67e56322a9bc": 200,
        "c63b68d6-6cb0-4636-8f08-673610064866": 100
      },
      "participants": [
        {
          "userId": "0536f06a-b2cd-4510-8df6-49bec2bc3531",
          "joinedAt": "2026-06-05T04:12:48.616Z"
        },
        {
          "userId": "4c333018-8317-4aa3-ae91-fe68242bd400",
          "joinedAt": "2026-06-05T04:13:22.301Z"
        }
      ],
      "standings": {
        "0536f06a-b2cd-4510-8df6-49bec2bc3531": {
          "score": 0,
          "solvedProblemIds": [],
          "lastAcceptedAt": null
        },
        "4c333018-8317-4aa3-ae91-fe68242bd400": {
          "score": 200,
          "solvedProblemIds": [
            "19635183-7f00-44d4-a48c-67e56322a9bc"
          ],
          "lastAcceptedAt": "2026-06-05T04:13:41.399Z"
        }
      },
      "createdAt": "2026-06-05T04:12:48.616Z",
      "startsAt": "2026-06-05T04:12:48.616Z",
      "endsAt": "2026-06-05T04:42:48.616Z"
    }
  ]
}